{"new": [{"new": "2093", "possible_mappings": {}}, {"new": "5271", "possible_mappings": {}}, {"new": "10227", "possible_mappings": {}}, {"new": "10635", "possible_mappings": {}}, {"new": "16596", "possible_mappings": {}}, {"new": "20838", "possible_mappings": {}}, {"new": "23951", "possible_mappings": {}}, {"new": "28970", "possible_mappings": {}}, {"new": "29170", "possible_mappings": {}}, {"new": "31957", "possible_mappings": {}}, {"new": "33317", "possible_mappings": {}}, {"new": "34230", "possible_mappings": {}}, {"new": "34865", "possible_mappings": {}}, {"new": "41205", "possible_mappings": {}}, {"new": "43022", "possible_mappings": {}}, {"new": "45550", "possible_mappings": {}}, {"new": "47759", "possible_mappings": {}}, {"new": "57572", "possible_mappings": {}}, {"new": "62319", "possible_mappings": {}}, {"new": "62834", "possible_mappings": {}}, {"new": "70390", "possible_mappings": {}}, {"new": "71609", "possible_mappings": {}}, {"new": "74869", "possible_mappings": {}}, {"new": "77422", "possible_mappings": {}}, {"new": "82429", "possible_mappings": {}}, {"new": "83970", "possible_mappings": {}}, {"new": "85353", "possible_mappings": {}}, {"new": "89247", "possible_mappings": {}}, {"new": "98135", "possible_mappings": {}}, {"new": "99976", "possible_mappings": {}}], "mapped": {"35864": {"new": "93197", "possible_mappings": {"35864": 1.0}}, "3083": {"new": "75708", "possible_mappings": {"3083": 0.9230769230769231, "7204": 0.8571428571428571, "24382": 0.8571428571428571, "58718": 0.8571428571428571}}}}